xiangting/__init__.py
xiangting/__init__.pyi
xiangting/py.typed
xiangting/xiangting.cpython-313t-aarch64-linux-gnu.so
xiangting-5.0.3.dist-info/METADATA
xiangting-5.0.3.dist-info/WHEEL
xiangting-5.0.3.dist-info/licenses/LICENSE
xiangting-5.0.3.dist-info/licenses/THIRD-PARTY-NOTICES.md
xiangting-5.0.3.dist-info/RECORD
