Metadata-Version: 2.4
Name: xiangting
Version: 5.0.3
Classifier: Development Status :: 5 - Production/Stable
Classifier: Intended Audience :: Developers
Classifier: Programming Language :: Rust
Classifier: Programming Language :: Python :: Implementation :: CPython
Classifier: Programming Language :: Python :: 3 :: Only
Classifier: Programming Language :: Python :: 3.12
Classifier: Programming Language :: Python :: 3.13
Classifier: Programming Language :: Python :: 3.14
Classifier: Topic :: Games/Entertainment :: Board Games
License-File: LICENSE
License-File: THIRD-PARTY-NOTICES.md
Summary: Python bindings for xiangting
Keywords: mahjong,riichi,shanten,xiangting
Author: Apricot S.
License-Expression: MIT
Requires-Python: >=3.12
Project-URL: Repository, https://github.com/Apricot-S/xiangting-py
